README.md
setup.py
jaygents/base.py
jaygents/model_based.py
jaygents.egg-info/PKG-INFO
jaygents.egg-info/SOURCES.txt
jaygents.egg-info/dependency_links.txt
jaygents.egg-info/requires.txt
jaygents.egg-info/top_level.txt